LICENSE
README.md
pyproject.toml
setup.py
eccovjson/Coverage.py
eccovjson/CoverageCollection.py
eccovjson/__init__.py
eccovjson/api.py
eccovjson/version.py
eccovjson.egg-info/PKG-INFO
eccovjson.egg-info/SOURCES.txt
eccovjson.egg-info/dependency_links.txt
eccovjson.egg-info/not-zip-safe
eccovjson.egg-info/top_level.txt
eccovjson/decoder/BoundingBox.py
eccovjson/decoder/Frame.py
eccovjson/decoder/TimeSeries.py
eccovjson/decoder/VerticalProfile.py
eccovjson/decoder/__init__.py
eccovjson/decoder/decoder.py
eccovjson/encoder/BoundingBox.py
eccovjson/encoder/Frame.py
eccovjson/encoder/TimeSeries.py
eccovjson/encoder/VerticalProfile.py
eccovjson/encoder/__init__.py
eccovjson/encoder/encoder.py