Metadata-Version: 1.0
Name: eccovjson
Version: 0.0.1
Summary: ECMWF library for encoding and decoding coerageJSON files/objects of meteorlogical features such as                    vertical profiles and time series.
Home-page: https://github.com/ecmwf/eccovjson
Author: ECMWF
Author-email: James.Hawkes@ecmwf.int, Adam.Warde@ecmwf.int, Mathilde.Leuridan@ecmwf.int
License: UNKNOWN
Platform: UNKNOWN
